sphinx_needs_extensions/__init__.py
sphinx_needs_extensions/communication.py
sphinx_needs_extensions/exceptions.py
sphinx_needs_extensions/extension.py
sphinx_needs_extensions/util.py
sphinx_needs_extensions-0.1.0.dist-info/LICENSE
sphinx_needs_extensions-0.1.0.dist-info/WHEEL
sphinx_needs_extensions-0.1.0.dist-info/METADATA
sphinx_needs_extensions-0.1.0.dist-info/RECORD
